odoo/addons/stock_picking_status_notification/README.rst
odoo/addons/stock_picking_status_notification/__init__.py
odoo/addons/stock_picking_status_notification/__manifest__.py
odoo/addons/stock_picking_status_notification/demo/stock_picking_notification_template_demo.xml
odoo/addons/stock_picking_status_notification/i18n/stock_picking_status_notification.pot
odoo/addons/stock_picking_status_notification/models/__init__.py
odoo/addons/stock_picking_status_notification/models/stock_picking.py
odoo/addons/stock_picking_status_notification/models/stock_picking_notification_template.py
odoo/addons/stock_picking_status_notification/readme/CONFIGURE.md
odoo/addons/stock_picking_status_notification/readme/CONTEXT.md
odoo/addons/stock_picking_status_notification/readme/DESCRIPTION.md
odoo/addons/stock_picking_status_notification/readme/USAGE.md
odoo/addons/stock_picking_status_notification/security/ir.model.access.csv
odoo/addons/stock_picking_status_notification/static/description/icon.png
odoo/addons/stock_picking_status_notification/static/description/index.html
odoo/addons/stock_picking_status_notification/tests/__init__.py
odoo/addons/stock_picking_status_notification/tests/test_notification_template.py
odoo/addons/stock_picking_status_notification/views/menuitems.xml
odoo/addons/stock_picking_status_notification/views/stock_picking_notification_template_view.xml
odoo_addon_stock_picking_status_notification-16.0.1.0.0.2.dist-info/METADATA
odoo_addon_stock_picking_status_notification-16.0.1.0.0.2.dist-info/WHEEL
odoo_addon_stock_picking_status_notification-16.0.1.0.0.2.dist-info/top_level.txt
odoo_addon_stock_picking_status_notification-16.0.1.0.0.2.dist-info/RECORD
