Metadata-Version: 2.1
Name: odoo-addon-stock_picking_status_notification
Version: 16.0.1.0.0.2
Summary: Notify selected internal users of changes in picking states
Home-page: https://github.com/OCA/stock-logistics-workflow
Author: Cetmix, Odoo Community Association (OCA)
Author-email: support@odoo-community.org
License: AGPL-3
Classifier: Programming Language :: Python
Classifier: Framework :: Odoo
Classifier: Framework :: Odoo :: 16.0
Classifier: License :: OSI Approved :: GNU Affero General Public License v3
Requires-Python: >=3.10
Requires-Dist: odoo-addon-web-notify<16.1dev,>=16.0dev
Requires-Dist: odoo<16.1dev,>=16.0a
